pyuvp/__init__.py
pyuvp/cli.py
pyuvp/pyuvp.py
pyuvp/ultrasound.py
pyuvp/ultrasound_doppler.py
pyuvp-0.1.0.dist-info/AUTHORS.rst
pyuvp-0.1.0.dist-info/LICENSE
pyuvp-0.1.0.dist-info/METADATA
pyuvp-0.1.0.dist-info/WHEEL
pyuvp-0.1.0.dist-info/entry_points.txt
pyuvp-0.1.0.dist-info/top_level.txt
pyuvp-0.1.0.dist-info/RECORD
