Metadata-Version: 2.1
Name: pyuvp
Version: 0.1.0
Summary: pyuvp is a python package with ultrasonic velocity profiler Doppler algorithms
Home-page: https://github.com/cesarofuchi/pyuvp
Author: Cesar Yutaka Ofuchi
Author-email: cesarofuchi@gmail.com
License: MIT license
Keywords: pyuvp
Platform: UNKNOWN
Classifier: Development Status :: 2 - Pre-Alpha
Classifier: Intended Audience :: Developers
Classifier: License :: OSI Approved :: MIT License
Classifier: Natural Language :: English
Classifier: Programming Language :: Python :: 3
Classifier: Programming Language :: Python :: 3.6
Classifier: Programming Language :: Python :: 3.7
Classifier: Programming Language :: Python :: 3.8
Requires-Python: >=3.6
License-File: LICENSE
License-File: AUTHORS.rst
Requires-Dist: Click (>=7.0)
Requires-Dist: numpy
Requires-Dist: scipy
Requires-Dist: matplotlib
